gobits/__init__.py
gobits/gobits.py
gobits-1.0.10.dist-info/LICENSE
gobits-1.0.10.dist-info/METADATA
gobits-1.0.10.dist-info/WHEEL
gobits-1.0.10.dist-info/top_level.txt
gobits-1.0.10.dist-info/RECORD
