Metadata-Version: 2.1
Name: gobits
Version: 1.0.10
Summary: Small Python package to add GCP metadata to pub/sub messages
Home-page: https://github.com/vwt-digital/gobits
Author: VWT Digital
Author-email: support@vwt.digital
License: GPLv3+
Classifier: Development Status :: 5 - Production/Stable
Classifier: Intended Audience :: Developers
Classifier: Natural Language :: English
Classifier: License :: OSI Approved :: GNU General Public License v3 or later (GPLv3+)
Classifier: Operating System :: OS Independent
Classifier: Programming Language :: Python :: 3.7
Classifier: Topic :: Software Development :: Libraries :: Python Modules
Classifier: Topic :: Scientific/Engineering
License-File: LICENSE
Requires-Dist: Werkzeug >=2.0.2
